weedata/__init__.py
weedata/client.py
weedata/fields.py
weedata/model.py
weedata/queries.py
weedata-0.2.7.dist-info/LICENSE
weedata-0.2.7.dist-info/METADATA
weedata-0.2.7.dist-info/WHEEL
weedata-0.2.7.dist-info/top_level.txt
weedata-0.2.7.dist-info/RECORD
