Metadata-Version: 2.1
Name: weedata
Version: 0.2.7
Summary: an ORM/ODM for Google Cloud Datastore/MongoDB/redis, featuring a compatible interface with Peewee.
Author-email: cdhigh <akindleear@gmail.com>
License: MIT License
Project-URL: Homepage, https://github.com/cdhigh/weedata
Project-URL: Issues, https://github.com/cdhigh/weedata/issues
Keywords: peewee,ORM,ODM,google cloud datastore,MongoDB,redis
Classifier: License :: OSI Approved :: MIT License
Classifier: Intended Audience :: Developers
Classifier: Operating System :: OS Independent
Classifier: Natural Language :: English
Classifier: Topic :: Database
Classifier: Topic :: Database :: Front-Ends
Classifier: Programming Language :: Python
Classifier: Programming Language :: Python :: 3
Classifier: Programming Language :: Python :: 3.6
Classifier: Programming Language :: Python :: 3.7
Classifier: Programming Language :: Python :: 3.8
Classifier: Programming Language :: Python :: 3.9
Classifier: Programming Language :: Python :: 3.10
Classifier: Programming Language :: Python :: 3.11
Classifier: Programming Language :: Python :: 3.12
Classifier: Topic :: Software Development :: Libraries
Requires-Python: >=3.6
License-File: LICENSE
